pyfragments_xwkuang5/__init__.py
pyfragments_xwkuang5/requirements.txt
pyfragments_xwkuang5/algo/__init__.py
pyfragments_xwkuang5/algo/bound.py
pyfragments_xwkuang5/algo/graph.py
pyfragments_xwkuang5/algo/hash_table.py
pyfragments_xwkuang5/algo/k_largest_benchmark.py
pyfragments_xwkuang5/algo/kmp.py
pyfragments_xwkuang5/algo/lazy_segment_tree.py
pyfragments_xwkuang5/algo/mst.py
pyfragments_xwkuang5/algo/online_median.py
pyfragments_xwkuang5/algo/permute.py
pyfragments_xwkuang5/algo/priority_queue.py
pyfragments_xwkuang5/algo/search.py
pyfragments_xwkuang5/algo/segment_tree.py
pyfragments_xwkuang5/algo/sort.py
pyfragments_xwkuang5/algo/topk.py
pyfragments_xwkuang5/algo/tree.py
pyfragments_xwkuang5/algo/trie.py
pyfragments_xwkuang5/algo/utils.py
pyfragments_xwkuang5/ml/AdaBoost.py
pyfragments_xwkuang5/ml/__init__.py
pyfragments_xwkuang5/ml/bayesnet.py
pyfragments_xwkuang5/ml/coin_tossing_EM.py
pyfragments_xwkuang5/ml/compare_gaussian_and_t_distribution.m
pyfragments_xwkuang5/ml/fit_normal_and_t_distribution.py
pyfragments_xwkuang5/ml/gen_data.m
pyfragments_xwkuang5/ml/gen_data.py
pyfragments_xwkuang5/ml/gen_gaussian_kernel.py
pyfragments_xwkuang5/ml/gibbs_sampling_experiment.py
pyfragments_xwkuang5/ml/kernel_density_estimation.py
pyfragments_xwkuang5/ml/learning_xor.py
pyfragments_xwkuang5/ml/loss_function_plot.py
pyfragments_xwkuang5/ml/multiarm_bandits.py
pyfragments_xwkuang5/ml/multilayer_nn.m
pyfragments_xwkuang5/ml/multilayer_nn.py
pyfragments_xwkuang5/ml/nn_utilities.py
pyfragments_xwkuang5/ml/over_sampling_by_replication.py
pyfragments_xwkuang5/ml/requirements.txt
pyfragments_xwkuang5/ml/simple_experiment_with_gnb.py
pyfragments_xwkuang5/ml/stacking.py
pyfragments_xwkuang5/ml/train_nn.py
pyfragments_xwkuang5/ml/figures/AdaBoost300WeakLearners.png
pyfragments_xwkuang5/ml/figures/multi-armed_experiment.png
pyfragments_xwkuang5/ml/figures/nb_model_repeated_features.png
pyfragments_xwkuang5/pattern/actor.py
pyfragments_xwkuang5/pattern/visitor_generator.py
pyfragments_xwkuang5-0.0.3.dist-info/METADATA
pyfragments_xwkuang5-0.0.3.dist-info/WHEEL
pyfragments_xwkuang5-0.0.3.dist-info/licenses/LICENSE
pyfragments_xwkuang5-0.0.3.dist-info/RECORD
