Metadata-Version: 2.1
Name: pyfragments_xwkuang5
Version: 0.0.3
Summary: Python code fragments
Project-URL: Homepage, https://github.com/xwkuang5/fragments/python
Project-URL: Bug Tracker, https://github.com/xwkuang5/fragments/issues
Author-email: Louis Kuang <louisconfussing@gmail.com>
License-File: LICENSE
Classifier: License :: OSI Approved :: MIT License
Classifier: Operating System :: OS Independent
Classifier: Programming Language :: Python :: 3
Requires-Python: >=3.7
